pyfiglets/__init__.py
pyfiglets/__main__.py
pyfiglets/test.py
pyfiglets/version.py
pyfiglets/fonts/1943____.flf
pyfiglets/fonts/1row.flf
pyfiglets/fonts/3-d.flf
pyfiglets/fonts/3d-ascii.flf
pyfiglets/fonts/3d_diagonal.flf
pyfiglets/fonts/3x5.flf
pyfiglets/fonts/4max.flf
pyfiglets/fonts/4x4_offr.flf
pyfiglets/fonts/5lineoblique.flf
pyfiglets/fonts/5x7.flf
pyfiglets/fonts/5x8.flf
pyfiglets/fonts/64f1____.flf
pyfiglets/fonts/6x10.flf
pyfiglets/fonts/6x9.flf
pyfiglets/fonts/__init__.py
pyfiglets/fonts/a_zooloo.flf
pyfiglets/fonts/acrobatic.flf
pyfiglets/fonts/advenger.flf
pyfiglets/fonts/alligator.flf
pyfiglets/fonts/alligator2.flf
pyfiglets/fonts/alpha.flf
pyfiglets/fonts/alphabet.flf
pyfiglets/fonts/amc_3_line.flf
pyfiglets/fonts/amc_3_liv1.flf
pyfiglets/fonts/amc_aaa01.flf
pyfiglets/fonts/amc_neko.flf
pyfiglets/fonts/amc_razor.flf
pyfiglets/fonts/amc_razor2.flf
pyfiglets/fonts/amc_slash.flf
pyfiglets/fonts/amc_slider.flf
pyfiglets/fonts/amc_thin.flf
pyfiglets/fonts/amc_tubes.flf
pyfiglets/fonts/amc_untitled.flf
pyfiglets/fonts/ansi_regular.flf
pyfiglets/fonts/ansi_shadow.flf
pyfiglets/fonts/aquaplan.flf
pyfiglets/fonts/arrows.flf
pyfiglets/fonts/asc_____.flf
pyfiglets/fonts/ascii___.flf
pyfiglets/fonts/ascii_new_roman.flf
pyfiglets/fonts/assalt_m.flf
pyfiglets/fonts/asslt__m.flf
pyfiglets/fonts/atc_____.flf
pyfiglets/fonts/atc_gran.flf
pyfiglets/fonts/avatar.flf
pyfiglets/fonts/b1ff.flf
pyfiglets/fonts/b_m__200.flf
pyfiglets/fonts/banner.flf
pyfiglets/fonts/banner3-D.flf
pyfiglets/fonts/banner3.flf
pyfiglets/fonts/banner4.flf
pyfiglets/fonts/barbwire.flf
pyfiglets/fonts/basic.flf
pyfiglets/fonts/battle_s.flf
pyfiglets/fonts/battlesh.flf
pyfiglets/fonts/baz__bil.flf
pyfiglets/fonts/bear.flf
pyfiglets/fonts/beer_pub.flf
pyfiglets/fonts/bell.flf
pyfiglets/fonts/benjamin.flf
pyfiglets/fonts/big.flf
pyfiglets/fonts/big_money-ne.flf
pyfiglets/fonts/big_money-nw.flf
pyfiglets/fonts/big_money-se.flf
pyfiglets/fonts/big_money-sw.flf
pyfiglets/fonts/bigchief.flf
rich_figlet-0.0.2.dist-info/licenses/LICENSE
rich_figlet-0.0.2.dist-info/METADATA
rich_figlet-0.0.2.dist-info/WHEEL
rich_figlet-0.0.2.dist-info/top_level.txt
rich_figlet-0.0.2.dist-info/RECORD
