Metadata-Version: 2.4
Name: rich-figlet
Version: 0.0.2
Summary: Pure Python FIGlets Implementation
Author-email: Gary Clark <gary@airoda.com>
License-Expression: MIT
Classifier: Development Status :: 5 - Production/Stable
Classifier: Environment :: Console
Classifier: Intended Audience :: Developers
Classifier: Natural Language :: English
Classifier: Natural Language :: Japanese
Classifier: Natural Language :: Bulgarian
Classifier: Natural Language :: Bosnian
Classifier: Natural Language :: Macedonian
Classifier: Natural Language :: Russian
Classifier: Natural Language :: Serbian
Classifier: Operating System :: Unix
Classifier: Programming Language :: Python
Classifier: Programming Language :: Python :: 3
Classifier: Programming Language :: Python :: 3.7
Classifier: Programming Language :: Python :: 3.8
Classifier: Programming Language :: Python :: 3.9
Classifier: Programming Language :: Python :: 3.10
Classifier: Programming Language :: Python :: 3.11
Classifier: Topic :: Text Processing
Classifier: Topic :: Text Processing :: Fonts
Requires-Python: >=3.9
License-File: LICENSE
Dynamic: license-file
